doppel/__init__.py
doppel/archive.py
doppel/driver.py
doppel/version.py
doppel-0.5.0.dist-info/LICENSE
doppel-0.5.0.dist-info/METADATA
doppel-0.5.0.dist-info/WHEEL
doppel-0.5.0.dist-info/entry_points.txt
doppel-0.5.0.dist-info/top_level.txt
doppel-0.5.0.dist-info/RECORD
