Metadata-Version: 2.1
Name: doppel
Version: 0.5.0
Summary: A friendly file copier/installer
Home-page: https://github.com/jimporter/doppel
Author: Jim Porter
Author-email: itsjimporter@gmail.com
License: BSD
Keywords: file copier and installer
Platform: UNKNOWN
Classifier: Development Status :: 4 - Beta
Classifier: Intended Audience :: Developers
Classifier: Topic :: Software Development :: Build Tools
Classifier: License :: OSI Approved :: BSD License
Classifier: Programming Language :: Python :: 3
Classifier: Programming Language :: Python :: 3.5
Classifier: Programming Language :: Python :: 3.6
Classifier: Programming Language :: Python :: 3.7
Classifier: Programming Language :: Python :: 3.8
Requires-Dist: elevate (>=0.1.2)
Provides-Extra: dev
Requires-Dist: coverage ; extra == 'dev'
Requires-Dist: flake8 (>=3.0) ; extra == 'dev'
Requires-Dist: pypandoc (>=1.4) ; extra == 'dev'
Provides-Extra: test
Requires-Dist: coverage ; extra == 'test'
Requires-Dist: flake8 (>=3.0) ; extra == 'test'
